kombine/__init__.py
kombine/command_line_interface.py
kombine/datacard.py
kombine/discrete_optimization.py
kombine/kaplan_meier.py
kombine/kaplan_meier_MINLP.py
kombine/kaplan_meier_likelihood.py
kombine/kaplan_meier_p_value_MINLP.py
kombine/utilities.py
kombinekm-2.0.0.dist-info/licenses/LICENSE
kombinekm-2.0.0.dist-info/licenses/NOTICE.txt
roc_picker/__init__.py
roc_picker/command_line_interface.py
roc_picker/continuous_distributions.py
roc_picker/datacard.py
roc_picker/delta_functions.py
roc_picker/discrete.py
roc_picker/discrete_base.py
roc_picker/systematics_mc.py
kombinekm-2.0.0.dist-info/METADATA
kombinekm-2.0.0.dist-info/WHEEL
kombinekm-2.0.0.dist-info/entry_points.txt
kombinekm-2.0.0.dist-info/top_level.txt
kombinekm-2.0.0.dist-info/RECORD
