Metadata-Version: 2.4
Name: kombinekm
Version: 2.0.0
Summary: KoMbine is a software package for propagating statistical and systematic uncertainties in a biomedical analysis. KoMbine provides Kaplan-Meier curve analysis functionality, while ROC Picker provides similar functionality for ROC curves.
Author-email: Heshy Roskes <heshyr@gmail.com>
License:                                  Apache License
Project-URL: Homepage, https://github.com/AstroPathJHU/KoMbine
Project-URL: Repository, https://github.com/AstroPathJHU/KoMbine
Classifier: Development Status :: 4 - Beta
Classifier: Intended Audience :: Science/Research
Classifier: License :: OSI Approved :: Apache Software License
Classifier: Programming Language :: Python :: 3
Classifier: Programming Language :: Python :: 3.8
Classifier: Programming Language :: Python :: 3.9
Classifier: Programming Language :: Python :: 3.10
Classifier: Programming Language :: Python :: 3.11
Classifier: Programming Language :: Python :: 3.12
Requires-Python: >=3.8
License-File: LICENSE
License-File: NOTICE.txt
Requires-Dist: gurobipy
Requires-Dist: matplotlib
Requires-Dist: numpy
Requires-Dist: scipy>=1.15
Dynamic: license-file
